{
	"id": "9c494898-a795-422e-ac2a-1fdc8a6e777d",
	"name": "FakeAPI Local",
	"values": [
		{
			"key": "base_url",
			"value": "http://127.0.0.1:3000",
			"enabled": true
		},
		{
			"key": "password",
			"value": "53157f17-ccbb-41c9-a1cc-0f3e48dd44f7",
			"enabled": true
		},
		{
			"key": "username",
			"value": "43c47ee7-cc60-4ef5-b7f6-d5cf0749a953",
			"enabled": true
		}
	],
	"_postman_variable_scope": "environment",
	"_postman_exported_at": "2019-04-27T02:39:35.045Z",
	"_postman_exported_using": "Postman/7.0.9"
}